odoo/addons/easy_my_coop_loan_bba/README.rst
odoo/addons/easy_my_coop_loan_bba/__init__.py
odoo/addons/easy_my_coop_loan_bba/__manifest__.py
odoo/addons/easy_my_coop_loan_bba/i18n/easy_my_coop_loan_bba.pot
odoo/addons/easy_my_coop_loan_bba/models/__init__.py
odoo/addons/easy_my_coop_loan_bba/models/loan_issue_line.py
odoo/addons/easy_my_coop_loan_bba/readme/CONTRIBUTORS.rst
odoo/addons/easy_my_coop_loan_bba/readme/DESCRIPTION.rst
odoo/addons/easy_my_coop_loan_bba/static/description/index.html
odoo12_addon_easy_my_coop_loan_bba-12.0.1.0.0.99.dev4.dist-info/METADATA
odoo12_addon_easy_my_coop_loan_bba-12.0.1.0.0.99.dev4.dist-info/WHEEL
odoo12_addon_easy_my_coop_loan_bba-12.0.1.0.0.99.dev4.dist-info/top_level.txt
odoo12_addon_easy_my_coop_loan_bba-12.0.1.0.0.99.dev4.dist-info/RECORD
